{
    "Backend": [
        {
            "src": "https://upload.wikimedia.org/wikipedia/commons/c/c3/Python-logo-notext.svg",
            "alt": "Python"
        },
        {
            "src": "https://seeklogo.com/images/D/django-logo-F46C1DD95E-seeklogo.com.png",
            "alt": "Django"
        },
        {
            "src": "https://www.clipartkey.com/mpngs/b/145-1450071_flask-clip-art.png",
            "alt": "Flask"
        },
        {
            "src": "https://upload.wikimedia.org/wikipedia/commons/thumb/d/d9/Node.js_logo.svg/885px-Node.js_logo.svg.png",
            "alt": "Node.js"
        },
        {
            "src": "https://upload.wikimedia.org/wikipedia/commons/thumb/2/29/Postgresql_elephant.svg/810px-Postgresql_elephant.svg.png",
            "alt": "PostgreSQL"
        },
        {
            "src": "https://raw.githubusercontent.com/webpack/media/master/logo/icon-square-big.png",
            "alt": "Webpack"
        }
    ],
    "Frontend": [
        {
            "src": "https://www.w3.org/html/logo/downloads/HTML5_Logo_512.png",
            "alt": "HTML5"
        },
        {
            "src": "https://upload.wikimedia.org/wikipedia/commons/thumb/d/d5/CSS3_logo_and_wordmark.svg/544px-CSS3_logo_and_wordmark.svg.png",
            "alt": "CSS3"
        },
        {
            "src": "https://upload.wikimedia.org/wikipedia/commons/thumb/9/99/Unofficial_JavaScript_logo_2.svg/1024px-Unofficial_JavaScript_logo_2.svg.png",
            "alt": "JavaScript"
        },
        {
            "src": "https://raw.githubusercontent.com/jsx-ir/logo/master/jsx.png",
            "alt": "JSX"
        },
        {
            "src": "https://openjsf.org/wp-content/uploads/sites/84/2019/10/jquery-logo-vertical_large_square.png",
            "alt": "jQuery"
        },
        {
            "src": "https://cdn.worldvectorlogo.com/logos/react.svg",
            "alt": "React.js/React Native"
        },
        {
            "src": "https://upload.wikimedia.org/wikipedia/commons/thumb/b/b2/Bootstrap_logo.svg/800px-Bootstrap_logo.svg.png",
            "alt": "Bootstrap"
        },
        {
            "src": "https://mdbootstrap.com/img/logo/mdb-transparent-big.png",
            "alt": "Material Design Bootstrap"
        }
    ],
    "Data & Vis": [
        {
            "src": "https://www.numfocus.org/wp-content/uploads/2016/07/pandas-logo-300.png",
            "alt": "Pandas"
        },
        {
            "src": "https://upload.wikimedia.org/wikipedia/commons/0/01/Created_with_Matplotlib-logo.svg",
            "alt": "Matplotlib"
        },
        {
            "src": "https://upload.wikimedia.org/wikipedia/commons/thumb/a/ae/Keras_logo.svg/768px-Keras_logo.svg.png",
            "alt": "Keras"
        },
        {
            "src": "https://upload.wikimedia.org/wikipedia/commons/2/2d/Tensorflow_logo.svg",
            "alt": "TensorFlow"
        },
        {
            "src": "https://seeklogo.com/images/M/mapbox-logo-D6FDDD219C-seeklogo.com.png",
            "alt": "Mapbox"
        },
        {
            "src": "https://upload.wikimedia.org/wikipedia/commons/3/32/OpenCV_Logo_with_text_svg_version.svg",
            "alt": "OpenCV"
        }
    ],
    "CI/CD & Platforms": [
        {
            "src": "https://git-scm.com/images/logos/downloads/Git-Icon-1788C.png",
            "alt": "Git"
        },
        {
            "src": "https://image.flaticon.com/icons/png/512/37/37318.png",
            "alt": "GitHub"
        },
        {
            "src": "https://cdn.freebiesupply.com/logos/large/2x/codecov-logo-png-transparent.png",
            "alt": "Codecov"
        },
        {
            "src": "https://dab1nmslvvntp.cloudfront.net/wp-content/uploads/2016/04/1461122387heroku-logo.jpg",
            "alt": "Heroku"
        },
        {
            "src": "https://res-1.cloudinary.com/crunchbase-production/image/upload/c_lpad,h_400,w_400,f_auto,b_white,q_auto:eco/dtokjerhk1dxyludtlwc",
            "alt": "Vercel (formerly Zeit Now)"
        },
        {
            "src": "https://assets.brandfolder.com/otz5mn-bw4j2w-6jzqo8/original/circle-logo-badge-black.png",
            "alt": "CircleCI"
        },
        {
            "src": "https://travis-ci.org/images/logos/TravisCI-Mascot-1.png",
            "alt": "Travis CI"
        },
        {
            "src": "https://res-4.cloudinary.com/crunchbase-production/image/upload/c_lpad,h_400,w_400,f_auto,b_white,q_auto:eco/rwgv0yumrzt6uuce9jtm",
            "alt": "Percy"
        },
        {
            "src": "https://www.docker.com/sites/default/files/d8/2019-07/Moby-logo.png",
            "alt": "Docker"
        }
    ]
}
